mypackage/__init__.py
mypackage/__main__.py
mypackage/test.py
mypackage_xavier/__init__.py
mypackage_xavier/__main__.py
mypackage_xavier/test.py
mypackage_xavier-0.1.dist-info/LICENCE.txt.rtf
mypackage_xavier-0.1.dist-info/METADATA
mypackage_xavier-0.1.dist-info/WHEEL
mypackage_xavier-0.1.dist-info/top_level.txt
mypackage_xavier-0.1.dist-info/RECORD
