Metadata-Version: 2.1
Name: mypackage-xavier
Version: 0.1
Summary: Testing installation of Package
Author: auth
Author-email: author@email.com
License: MIT
License-File: LICENCE.txt.rtf
